nedo_vision_annotator/__init__.py
nedo_vision_annotator/annotator_service.py
nedo_vision_annotator/cli.py
nedo_vision_annotator/annotator/AnnotatorManager.py
nedo_vision_annotator/annotator/AutoAnnotationManager.py
nedo_vision_annotator/annotator/__init__.py
nedo_vision_annotator/config/ConfigurationManager.py
nedo_vision_annotator/config/__init__.py
nedo_vision_annotator/core/DatasetManager.py
nedo_vision_annotator/core/ModelLoader.py
nedo_vision_annotator/core/__init__.py
nedo_vision_annotator/database/__init__.py
nedo_vision_annotator/database/base.py
nedo_vision_annotator/database/session.py
nedo_vision_annotator/database/entities/DatasetAnnotation.py
nedo_vision_annotator/database/entities/__init__.py
nedo_vision_annotator/database/repositories/DatasetAnnotationRepository.py
nedo_vision_annotator/database/repositories/__init__.py
nedo_vision_annotator/detection/BaseDetector.py
nedo_vision_annotator/detection/RFDETRDetector.py
nedo_vision_annotator/detection/YOLODetector.py
nedo_vision_annotator/detection/__init__.py
nedo_vision_annotator/initializer/AppInitializer.py
nedo_vision_annotator/initializer/__init__.py
nedo_vision_annotator/models/AIModel.py
nedo_vision_annotator/models/__init__.py
nedo_vision_annotator/services/AnnotatorGrpcClient.py
nedo_vision_annotator/services/AnnotatorService_pb2.py
nedo_vision_annotator/services/AnnotatorService_pb2.pyi
nedo_vision_annotator/services/AnnotatorService_pb2_grpc.py
nedo_vision_annotator/services/AnnotatorService_pb2_grpc.pyi
nedo_vision_annotator/services/AutoAnnotationGrpcClient.py
nedo_vision_annotator/services/AutoAnnotation_pb2.py
nedo_vision_annotator/services/AutoAnnotation_pb2.pyi
nedo_vision_annotator/services/AutoAnnotation_pb2_grpc.py
nedo_vision_annotator/services/AutoAnnotation_pb2_grpc.pyi
nedo_vision_annotator/services/GrpcClientBase.py
nedo_vision_annotator/services/RabbitMQConsumer.py
nedo_vision_annotator/services/RabbitMQPublisher.py
nedo_vision_annotator/services/__init__.py
nedo_vision_annotator-1.1.1.dist-info/licenses/LICENSE
nedo_vision_annotator-1.1.1.dist-info/METADATA
nedo_vision_annotator-1.1.1.dist-info/WHEEL
nedo_vision_annotator-1.1.1.dist-info/entry_points.txt
nedo_vision_annotator-1.1.1.dist-info/top_level.txt
nedo_vision_annotator-1.1.1.dist-info/RECORD
