Metadata-Version: 2.4
Name: nedo-vision-annotator
Version: 1.1.1
Summary: Nedo Vision Annotator Service for Automated Image Annotation
Author-email: Willy Achmat Fauzi <willy.achmat@gmail.com>
Maintainer-email: Willy Achmat Fauzi <willy.achmat@gmail.com>
License-Expression: MIT
Project-URL: Homepage, https://gitlab.com/sindika/research/nedo-vision/nedo-vision-annotator
Project-URL: Documentation, https://gitlab.com/sindika/research/nedo-vision/nedo-vision-annotator/-/blob/main/README.md
Project-URL: Repository, https://gitlab.com/sindika/research/nedo-vision/nedo-vision-annotator
Project-URL: Bug Reports, https://gitlab.com/sindika/research/nedo-vision/nedo-vision-annotator/-/issues
Keywords: computer-vision,machine-learning,ai,annotation,deep-learning,object-detection,image-processing,yolo,rfdetr
Classifier: Development Status :: 4 - Beta
Classifier: Intended Audience :: Developers
Classifier: Operating System :: OS Independent
Classifier: Operating System :: POSIX :: Linux
Classifier: Operating System :: Microsoft :: Windows
Classifier: Operating System :: MacOS
Classifier: Programming Language :: Python :: 3
Classifier: Programming Language :: Python :: 3 :: Only
Classifier: Programming Language :: Python :: 3.8
Classifier: Programming Language :: Python :: 3.9
Classifier: Programming Language :: Python :: 3.10
Classifier: Programming Language :: Python :: 3.11
Classifier: Programming Language :: Python :: 3.12
Classifier: Programming Language :: Python :: 3.13
Classifier: Topic :: Software Development :: Libraries :: Python Modules
Classifier: Topic :: Scientific/Engineering :: Artificial Intelligence
Classifier: Topic :: Scientific/Engineering :: Image Recognition
Classifier: Topic :: System :: Hardware
Classifier: Environment :: GPU
Classifier: Environment :: No Input/Output (Daemon)
Requires-Python: >=3.8
License-File: LICENSE
Requires-Dist: grpcio>=1.50.0
Requires-Dist: grpcio-tools>=1.50.0
Requires-Dist: protobuf>=4.21.0
Requires-Dist: pika>=1.3.0
Requires-Dist: torch>=2.0.0
Requires-Dist: torchvision>=0.15.0
Requires-Dist: ultralytics>=8.0.0
Requires-Dist: opencv-python>=4.7.0
Requires-Dist: numpy<2.0.0,>=1.24.0
Requires-Dist: sqlalchemy>=2.0.0
Requires-Dist: psutil>=5.9.0
Requires-Dist: groundingdino-py==0.4.0
Provides-Extra: rfdetr
Requires-Dist: rfdetr<2.0.0,>=1.2.0; extra == "rfdetr"
Provides-Extra: dev
Requires-Dist: pytest>=7.0.0; extra == "dev"
Requires-Dist: black>=22.0.0; extra == "dev"
Requires-Dist: isort>=5.10.0; extra == "dev"
Requires-Dist: mypy>=0.950; extra == "dev"
Requires-Dist: flake8>=4.0.0; extra == "dev"
Requires-Dist: pre-commit>=2.17.0; extra == "dev"
Dynamic: license-file
